my_own_package/__init__.py
Mihai_Dorin_Beniamin_own_package-0.1.0.dist-info/METADATA
Mihai_Dorin_Beniamin_own_package-0.1.0.dist-info/WHEEL
Mihai_Dorin_Beniamin_own_package-0.1.0.dist-info/top_level.txt
Mihai_Dorin_Beniamin_own_package-0.1.0.dist-info/RECORD
