Metadata-Version: 2.1
Name: Mihai-Dorin-Beniamin-own-package
Version: 0.1.0
Summary: my_frist_package
Author: Mihai Dorin
Author-email: mihaidorin9727@yahoo.com
